sphinxcontrib/cloudformationyaml/__init__.py
sphinxcontrib_cloudformationyaml-0.2.0.dist-info/DESCRIPTION.rst
sphinxcontrib_cloudformationyaml-0.2.0.dist-info/LICENSE.txt
sphinxcontrib_cloudformationyaml-0.2.0.dist-info/METADATA
sphinxcontrib_cloudformationyaml-0.2.0.dist-info/RECORD
sphinxcontrib_cloudformationyaml-0.2.0.dist-info/WHEEL
sphinxcontrib_cloudformationyaml-0.2.0.dist-info/metadata.json
sphinxcontrib_cloudformationyaml-0.2.0.dist-info/top_level.txt
