Metadata-Version: 2.0
Name: sphinxcontrib-cloudformationyaml
Version: 0.2.0
Summary: Sphinx extension to generate docs from cloudformation descriptions and comments
Home-page: https://github.com/monk-ee/sphinxcontrib-cloudformationyaml
Author: Lyndon Swan
Author-email: magic.monkee.magic@gmail.com
License: MIT
Platform: any
Classifier: Development Status :: 3 - Alpha
Classifier: Framework :: Sphinx :: Extension
Classifier: Intended Audience :: System Administrators
Classifier: License :: OSI Approved :: MIT License
Classifier: Topic :: Documentation
Requires-Dist: Sphinx
Requires-Dist: ruamel.yaml
